glasgow_live/__init__.py
glasgow_live/adapters.py
glasgow_live/feed.py
glasgow_live/models.py
glasgow_live/rss_links.py
glasgow_live-0.0.11.dist-info/LICENSE.txt
glasgow_live-0.0.11.dist-info/METADATA
glasgow_live-0.0.11.dist-info/WHEEL
glasgow_live-0.0.11.dist-info/top_level.txt
glasgow_live-0.0.11.dist-info/RECORD
